pre_commit_hooks/__init__.py
pre_commit_hooks/configs/gitignore-generic
pre_commit_hooks/configs/gitignore-python
pre_commit_hooks/constants.py
pre_commit_hooks/hooks/__init__.py
pre_commit_hooks/hooks/add_future_import_annotations.py
pre_commit_hooks/hooks/add_hooks.py
pre_commit_hooks/hooks/check_versions_consistent.py
pre_commit_hooks/hooks/format_pre_commit_config.py
pre_commit_hooks/hooks/format_requirements.py
pre_commit_hooks/hooks/replace_sequence_str.py
pre_commit_hooks/hooks/run_prek_autoupdate.py
pre_commit_hooks/hooks/run_uv_lock.py
pre_commit_hooks/hooks/run_version_bump.py
pre_commit_hooks/hooks/setup_bump_my_version.py
pre_commit_hooks/hooks/setup_ci_pull_request.py
pre_commit_hooks/hooks/setup_ci_push.py
pre_commit_hooks/hooks/setup_coverage.py
pre_commit_hooks/hooks/setup_direnv.py
pre_commit_hooks/hooks/setup_git.py
pre_commit_hooks/hooks/setup_just.py
pre_commit_hooks/hooks/setup_pre_commit.py
pre_commit_hooks/hooks/setup_pyproject.py
pre_commit_hooks/hooks/setup_pyright.py
pre_commit_hooks/hooks/setup_pytest.py
pre_commit_hooks/hooks/setup_readme.py
pre_commit_hooks/hooks/setup_ruff.py
pre_commit_hooks/hooks/update_ci_action_versions.py
pre_commit_hooks/hooks/update_ci_extensions.py
pre_commit_hooks/hooks/update_requirements.py
pre_commit_hooks/py.typed
pre_commit_hooks/types.py
pre_commit_hooks/utilities.py
dycw_pre_commit_hooks-0.14.129.dist-info/WHEEL
dycw_pre_commit_hooks-0.14.129.dist-info/entry_points.txt
dycw_pre_commit_hooks-0.14.129.dist-info/METADATA
dycw_pre_commit_hooks-0.14.129.dist-info/RECORD
