Metadata-Version: 2.3
Name: dycw-pre-commit-hooks
Version: 0.14.129
Summary: Pre-commit hooks
Author: Derek Wan
Author-email: Derek Wan <d.wan@icloud.com>
Requires-Dist: click>=8.3.1
Requires-Dist: dycw-utilities>=0.188.10
Requires-Dist: libcst>=1.8.6
Requires-Dist: orjson>=3.11.6
Requires-Dist: packaging>=26.0
Requires-Dist: pyyaml>=6.0.3
Requires-Dist: tomlkit>=0.14.0
Requires-Dist: xdg-base-dirs>=6.0.2
Requires-Dist: click==8.3.1 ; extra == 'cli'
Requires-Dist: dycw-utilities==0.188.10 ; extra == 'cli'
Requires-Dist: libcst==1.8.6 ; extra == 'cli'
Requires-Dist: orjson==3.11.6 ; extra == 'cli'
Requires-Dist: packaging==26.0 ; extra == 'cli'
Requires-Dist: pyyaml==6.0.3 ; extra == 'cli'
Requires-Dist: tomlkit==0.14.0 ; extra == 'cli'
Requires-Dist: xdg-base-dirs==6.0.2 ; extra == 'cli'
Requires-Python: >=3.12
Provides-Extra: cli
